<?xml version="1.0" encoding="utf-8"?>
<languages>
  <language name="日本語 (Japanese)" id="ja">
    <Commerce>
      <Checkout>
        <DataCash>
          <PaymentNotSpecified>お支払い情報が指定されていません。</PaymentNotSpecified>
          <PaymentNotAssociatedOrderGroup>注文グループを指定してから、お支払い手続きを行ってください。</PaymentNotAssociatedOrderGroup>
          <PaymentNotAssociatedOrderForm>注文フォームを指定してから、お支払い手続きを行ってください。</PaymentNotAssociatedOrderForm>
          <ProcessPaymentNullHttpContext>HttpContext.Current is null.</ProcessPaymentNullHttpContext>
          <NotEnoughStockWarning>支払いは完了しましたが、在庫が不足しています。 管理者までご連絡ください。</NotEnoughStockWarning>
          <CartValidationWarning>カートを処理する際にエラーが発生しました。</CartValidationWarning>
          <CreditCardEmpty>お支払いの詳細を入力してください。</CreditCardEmpty>
          <CommitTranErrorCartNull>Cart is null while processing successful transaction redirected back from DataCash</CommitTranErrorCartNull>
          <PaymentRejectedBy3rdMan>支払いの要求は、第三者サービスによって拒否されました。</PaymentRejectedBy3rdMan>
          <PaymentDetail>お支払いの詳細</PaymentDetail>
          <CardType>カードの種類:</CardType>
          <CardNumber>カード番号:</CardNumber>
          <ExpiryDate>有効期限:</ExpiryDate>
          <GenericError>DataCash でチェック アウトする際にエラーが発生しました。 お客様の情報を確認してください。</GenericError>
        </DataCash>
      </Checkout>
    </Commerce>
  </language>
</languages>
