<?xml version="1.0" encoding="utf-8"?>
<languages>
  <language name="español" id="es">
    <Commerce>
      <Checkout>
        <DIBS>
          <CancelMessage>Su pago ha sido rechazado o cancelado. Por favor, inténtelo de nuevo o elija otra forma de pago</CancelMessage>
          <DIBSSettingsError>Error en la configuración de la API de DIBS. Póngase en contacto con el administrador.</DIBSSettingsError>
          <DIBSText>DIBS</DIBSText>
          <PaymentNotSpecified>La información de pago no está especificada.</PaymentNotSpecified>
          <PaymentNotAssociatedOrderGroup>El pago debe estar asociado con un grupo de pedidos.</PaymentNotAssociatedOrderGroup>
          <PaymentNotAssociatedOrderForm>El pago debe estar asociado con un formulario de pedidos.</PaymentNotAssociatedOrderForm>
        </DIBS>
      </Checkout>
    </Commerce>
  </language>
</languages>